paddleaudio/__init__.py
paddleaudio/_extension.py
paddleaudio/_paddleaudio.so
paddleaudio/_internal/__init__.py
paddleaudio/_internal/module_utils.py
paddleaudio/backends/__init__.py
paddleaudio/backends/common.py
paddleaudio/backends/no_backend.py
paddleaudio/backends/soundfile_backend.py
paddleaudio/backends/sox_io_backend.py
paddleaudio/backends/utils.py
paddleaudio/compliance/__init__.py
paddleaudio/compliance/kaldi.py
paddleaudio/compliance/librosa.py
paddleaudio/datasets/__init__.py
paddleaudio/datasets/dataset.py
paddleaudio/datasets/esc50.py
paddleaudio/datasets/gtzan.py
paddleaudio/datasets/hey_snips.py
paddleaudio/datasets/rirs_noises.py
paddleaudio/datasets/tess.py
paddleaudio/datasets/urban_sound.py
paddleaudio/datasets/voxceleb.py
paddleaudio/features/__init__.py
paddleaudio/features/layers.py
paddleaudio/functional/__init__.py
paddleaudio/functional/functional.py
paddleaudio/functional/window.py
paddleaudio/kaldi/__init__.py
paddleaudio/kaldi/kaldi.py
paddleaudio/lib/libpaddleaudio.so
paddleaudio/metric/__init__.py
paddleaudio/metric/eer.py
paddleaudio/sox_effects/__init__.py
paddleaudio/sox_effects/sox_effects.py
paddleaudio/utils/__init__.py
paddleaudio/utils/download.py
paddleaudio/utils/env.py
paddleaudio/utils/error.py
paddleaudio/utils/log.py
paddleaudio/utils/numeric.py
paddleaudio/utils/sox_utils.py
paddleaudio/utils/tensor_utils.py
paddleaudio/utils/time.py
paddleaudio-1.1.0.dist-info/METADATA
paddleaudio-1.1.0.dist-info/WHEEL
paddleaudio-1.1.0.dist-info/top_level.txt
paddleaudio-1.1.0.dist-info/zip-safe
paddleaudio-1.1.0.dist-info/RECORD
